pipecashwallets/__init__.py
pipecashwallets/bitsv_wallet.py
pipecashwallets/bsv_rpc.py
pipecashwallets/btc_rpc.py
pipecashwallets/examples.py
pipecashwallets-0.1.2.1.dist-info/AUTHORS.rst
pipecashwallets-0.1.2.1.dist-info/LICENSE
pipecashwallets-0.1.2.1.dist-info/METADATA
pipecashwallets-0.1.2.1.dist-info/WHEEL
pipecashwallets-0.1.2.1.dist-info/top_level.txt
pipecashwallets-0.1.2.1.dist-info/RECORD
