Metadata-Version: 2.1
Name: pipecashwallets
Version: 0.1.2.1
Summary: A collection of wallet modules for PipeCaead http://pipe.cash/ for more information.
Home-page: https://github.com/Pipe-Cash/pipecashwallets
Author: Aleksandar Nikolaev Dinkov
Author-email: alexander.n.dinkov@gmail.com
License: MIT license
Keywords: pipecashwallets
Platform: UNKNOWN
Classifier: Development Status :: 2 - Pre-Alpha
Classifier: Intended Audience :: Developers
Classifier: Natural Language :: English
Classifier: Programming Language :: Python :: 3
Classifier: Programming Language :: Python :: 3.4
Classifier: Programming Language :: Python :: 3.5
Classifier: Programming Language :: Python :: 3.6
Classifier: Programming Language :: Python :: 3.7
Requires-Dist: python-bitcoinrpc
Requires-Dist: requests
